vsrc/cnn_defines.v
`define CNN_DATA_IN_W 8 /* 灰度数据8位 */
`define CNN_GRAY_BUFFER_ADDR_W 5 /* 灰度流缓存器地址宽度 */
`define CNN_IMG_IN_WIDTH 28 /* 输入图像宽 */
`define CNN_CONV1_OUT_W 192 /* 第一层输出6*32 */

conv_para/vsrc/graylinebuffer.v
/* 灰度流缓存 双口ram*/
`include "cnn_defines.v"
module graylinebuffer
#(
    parameter IMG_IN_WIDTH = 28
)
(
    clkw    ,
    w_en    ,
    waddr   ,
    din     ,

    clkr    ,
    r_en    ,
    raddr   ,
    dout
);
    input                                   clkw    ;
    input                                   clkr    ;
    input                                   w_en    ;
    input                                   r_en    ;
    input  [`CNN_GRAY_BUFFER_ADDR_W-1:0]    waddr   ;
    input  [`CNN_GRAY_BUFFER_ADDR_W-1:0]    raddr   ;
    input  [`CNN_DATA_IN_W-1:0]             din     ;

    output reg [`CNN_DATA_IN_W-1:0] dout;

    reg [`CNN_DATA_IN_W-1:0] buffer [IMG_IN_WIDTH-1:0];

    always@(posedge clkw) begin
        if(w_en)
            buffer[waddr] <= din;
        else
            ;
    end

    always@(posedge clkr) begin
        if(r_en)
            dout <= buffer[raddr];
        else
            ;
    end


endmodule

conv1.v
`include "cnn_defines.v"
`include "graylinebuffer.v"
module conv1(
    clk                 ,
    rst_n               ,

    cnn_data_in         ,
    cnn_data_in_valid   /*,

    cnn_data_out        ,
    cnn_data_out_valid*/
);

    input                           clk                 ;
    input                           rst_n               ;
    input   [`CNN_DATA_IN_W-1:0]    cnn_data_in         ;
    input                           cnn_data_in_valid   ;
    /*output  [`CNN_CONV1_OUT_W-1:0]  cnn_data_out        ;
    output reg                      cnn_data_out_valid  ;*/

    /*wire [31:0] data_out_array [5:0];/* 输出6通道 */

    /*======================= addr ============================*/
    reg [4:0]   wr_addr;
    reg [4:0]   rd_addr;
    wire [4:0] rd_addr_pre2 = wr_addr +2;
    always@(posedge clk, negedge rst_n)begin
        if(~rst_n)begin
            wr_addr <= 0;
            rd_addr <= 0;
        end
        else if(cnn_data_in_valid == 1'b1)begin
            //========== A ============
            if(wr_addr == 'd27)
                wr_addr <= 5'd0;
            else
                wr_addr <= wr_addr + 1'd1;
            //========== B ============
            if(rd_addr_pre2 > 'd27)
                rd_addr <= rd_addr_pre2 - 5'd28;
            else
                rd_addr <= rd_addr_pre2;
        end
    end
//======================= data ===============================
    wire    [7:0]   window_in[0:5-1];
    wire    [7:0]   window_out[0:5-1];
    assign  window_in[0]    = cnn_data_in;
    genvar k;
    generate
    for(k=1;k<5;k=k+1)begin
       assign    window_in[k]=window_out[k-1];
    end
    endgenerate
    
    
    //======================= Instance ===============================
    
    generate
    for (k=0;k<5;k=k+1)begin
    graylinebuffer graylinebuffer_U (
        .clkw (clk              ), 
        .w_en (cnn_data_in_valid), 
        .waddr(wr_addr          ), 
        .din  (window_in[k]     ), 
        .clkr (clk              ), 
        .r_en (1'b1             ), 
        .raddr(rd_addr          ), 
        .dout (window_out[k]    ) 
    );
    end
    endgenerate
    //======================= window ===============================
    reg signed [7:0] window[5-1:0][5-1:0];
    integer i,j;
    always@(posedge clk ,negedge rst_n)begin
        if(~rst_n)begin
            for(i=0;i<5;i=i+1)begin
                for(j=0;j<5;j=j+1)begin
                    window[i][j]<=0;
                end
            end
        end
        else if(cnn_data_in_valid == 1'b1 )begin
            for(i=0;i<5;i=i+1)begin
                window[i][0] <= window_in[i];
                for(j=1;j<5;j=j+1)begin
                    window[i][j]<=window[i][j-1];
                end
            end
        end
    end
endmodule

waveform.vcd
$version Generated by VerilatedVcd $end
$date Sun Mar  5 16:28:20 2023 $end
$timescale 1ps $end

 $scope module TOP $end
  $var wire  1 %" clk $end
  $var wire  8 '" cnn_data_in [7:0] $end
  $var wire  1 (" cnn_data_in_valid $end
  $var wire  1 &" rst_n $end
  $scope module conv1 $end
   $var wire  1 %" clk $end
   $var wire  8 '" cnn_data_in [7:0] $end
   $var wire  1 (" cnn_data_in_valid $end
   $var wire 32 < i [31:0] $end
   $var wire 32 = j [31:0] $end
   $var wire  5 #" rd_addr [4:0] $end
   $var wire  5 $" rd_addr_pre2 [4:0] $end
   $var wire  1 &" rst_n $end
   $var wire  8 # window(0)(0) [7:0] $end
   $var wire  8 $ window(0)(1) [7:0] $end
   $var wire  8 % window(0)(2) [7:0] $end
   $var wire  8 & window(0)(3) [7:0] $end
   $var wire  8 ' window(0)(4) [7:0] $end
   $var wire  8 ( window(1)(0) [7:0] $end
   $var wire  8 ) window(1)(1) [7:0] $end
   $var wire  8 * window(1)(2) [7:0] $end
   $var wire  8 + window(1)(3) [7:0] $end
   $var wire  8 , window(1)(4) [7:0] $end
   $var wire  8 - window(2)(0) [7:0] $end
   $var wire  8 . window(2)(1) [7:0] $end
   $var wire  8 / window(2)(2) [7:0] $end
   $var wire  8 0 window(2)(3) [7:0] $end
   $var wire  8 1 window(2)(4) [7:0] $end
   $var wire  8 2 window(3)(0) [7:0] $end
   $var wire  8 3 window(3)(1) [7:0] $end
   $var wire  8 4 window(3)(2) [7:0] $end
   $var wire  8 5 window(3)(3) [7:0] $end
   $var wire  8 6 window(3)(4) [7:0] $end
   $var wire  8 7 window(4)(0) [7:0] $end
   $var wire  8 8 window(4)(1) [7:0] $end
   $var wire  8 9 window(4)(2) [7:0] $end
   $var wire  8 : window(4)(3) [7:0] $end
   $var wire  8 ; window(4)(4) [7:0] $end
   $var wire  8 v! window_in(0) [7:0] $end
   $var wire  8 w! window_in(1) [7:0] $end
   $var wire  8 x! window_in(2) [7:0] $end
   $var wire  8 y! window_in(3) [7:0] $end
   $var wire  8 z! window_in(4) [7:0] $end
   $var wire  8 > window_out(0) [7:0] $end
   $var wire  8 ? window_out(1) [7:0] $end
   $var wire  8 @ window_out(2) [7:0] $end
   $var wire  8 A window_out(3) [7:0] $end
   $var wire  8 B window_out(4) [7:0] $end
   $var wire  5 "" wr_addr [4:0] $end
   $scope module genblk2(0) $end
    $scope module graylinebuffer_U $end
     $var wire  8 D buffer(0) [7:0] $end
     $var wire  8 E buffer(1) [7:0] $end
     $var wire  8 N buffer(10) [7:0] $end
     $var wire  8 O buffer(11) [7:0] $end
     $var wire  8 P buffer(12) [7:0] $end
     $var wire  8 Q buffer(13) [7:0] $end
     $var wire  8 R buffer(14) [7:0] $end
     $var wire  8 S buffer(15) [7:0] $end
     $var wire  8 T buffer(16) [7:0] $end
     $var wire  8 U buffer(17) [7:0] $end
     $var wire  8 V buffer(18) [7:0] $end
     $var wire  8 W buffer(19) [7:0] $end
     $var wire  8 F buffer(2) [7:0] $end
     $var wire  8 X buffer(20) [7:0] $end
     $var wire  8 Y buffer(21) [7:0] $end
     $var wire  8 Z buffer(22) [7:0] $end
     $var wire  8 [ buffer(23) [7:0] $end
     $var wire  8 \ buffer(24) [7:0] $end
     $var wire  8 ] buffer(25) [7:0] $end
     $var wire  8 ^ buffer(26) [7:0] $end
     $var wire  8 _ buffer(27) [7:0] $end
     $var wire  8 G buffer(3) [7:0] $end
     $var wire  8 H buffer(4) [7:0] $end
     $var wire  8 I buffer(5) [7:0] $end
     $var wire  8 J buffer(6) [7:0] $end
     $var wire  8 K buffer(7) [7:0] $end
     $var wire  8 L buffer(8) [7:0] $end
     $var wire  8 M buffer(9) [7:0] $end
     $var wire  1 %" clkr $end
     $var wire  1 %" clkw $end
     $var wire  8 {! din [7:0] $end
     $var wire  8 C dout [7:0] $end
     $var wire  1 )" r_en $end
     $var wire  5 #" raddr [4:0] $end
     $var wire  1 (" w_en $end
     $var wire  5 "" waddr [4:0] $end
    $upscope $end
   $upscope $end
   $scope module genblk2(1) $end
    $scope module graylinebuffer_U $end
     $var wire  8 a buffer(0) [7:0] $end
     $var wire  8 b buffer(1) [7:0] $end
     $var wire  8 k buffer(10) [7:0] $end
     $var wire  8 l buffer(11) [7:0] $end
     $var wire  8 m buffer(12) [7:0] $end
     $var wire  8 n buffer(13) [7:0] $end
     $var wire  8 o buffer(14) [7:0] $end
     $var wire  8 p buffer(15) [7:0] $end
     $var wire  8 q buffer(16) [7:0] $end
     $var wire  8 r buffer(17) [7:0] $end
     $var wire  8 s buffer(18) [7:0] $end
     $var wire  8 t buffer(19) [7:0] $end
     $var wire  8 c buffer(2) [7:0] $end
     $var wire  8 u buffer(20) [7:0] $end
     $var wire  8 v buffer(21) [7:0] $end
     $var wire  8 w buffer(22) [7:0] $end
     $var wire  8 x buffer(23) [7:0] $end
     $var wire  8 y buffer(24) [7:0] $end
     $var wire  8 z buffer(25) [7:0] $end
     $var wire  8 { buffer(26) [7:0] $end
     $var wire  8 | buffer(27) [7:0] $end
     $var wire  8 d buffer(3) [7:0] $end
     $var wire  8 e buffer(4) [7:0] $end
     $var wire  8 f buffer(5) [7:0] $end
     $var wire  8 g buffer(6) [7:0] $end
     $var wire  8 h buffer(7) [7:0] $end
     $var wire  8 i buffer(8) [7:0] $end
     $var wire  8 j buffer(9) [7:0] $end
     $var wire  1 %" clkr $end
     $var wire  1 %" clkw $end
     $var wire  8 |! din [7:0] $end
     $var wire  8 ` dout [7:0] $end
     $var wire  1 )" r_en $end
     $var wire  5 #" raddr [4:0] $end
     $var wire  1 (" w_en $end
     $var wire  5 "" waddr [4:0] $end
    $upscope $end
   $upscope $end
   $scope module genblk2(2) $end
    $scope module graylinebuffer_U $end
     $var wire  8 ~ buffer(0) [7:0] $end
     $var wire  8 !! buffer(1) [7:0] $end
     $var wire  8 *! buffer(10) [7:0] $end
     $var wire  8 +! buffer(11) [7:0] $end
     $var wire  8 ,! buffer(12) [7:0] $end
     $var wire  8 -! buffer(13) [7:0] $end
     $var wire  8 .! buffer(14) [7:0] $end
     $var wire  8 /! buffer(15) [7:0] $end
     $var wire  8 0! buffer(16) [7:0] $end
     $var wire  8 1! buffer(17) [7:0] $end
     $var wire  8 2! buffer(18) [7:0] $end
     $var wire  8 3! buffer(19) [7:0] $end
     $var wire  8 "! buffer(2) [7:0] $end
     $var wire  8 4! buffer(20) [7:0] $end
     $var wire  8 5! buffer(21) [7:0] $end
     $var wire  8 6! buffer(22) [7:0] $end
     $var wire  8 7! buffer(23) [7:0] $end
     $var wire  8 8! buffer(24) [7:0] $end
     $var wire  8 9! buffer(25) [7:0] $end
     $var wire  8 :! buffer(26) [7:0] $end
     $var wire  8 ;! buffer(27) [7:0] $end
     $var wire  8 #! buffer(3) [7:0] $end
     $var wire  8 $! buffer(4) [7:0] $end
     $var wire  8 %! buffer(5) [7:0] $end
     $var wire  8 &! buffer(6) [7:0] $end
     $var wire  8 '! buffer(7) [7:0] $end
     $var wire  8 (! buffer(8) [7:0] $end
     $var wire  8 )! buffer(9) [7:0] $end
     $var wire  1 %" clkr $end
     $var wire  1 %" clkw $end
     $var wire  8 }! din [7:0] $end
     $var wire  8 } dout [7:0] $end
     $var wire  1 )" r_en $end
     $var wire  5 #" raddr [4:0] $end
     $var wire  1 (" w_en $end
     $var wire  5 "" waddr [4:0] $end
    $upscope $end
   $upscope $end
   $scope module genblk2(3) $end
    $scope module graylinebuffer_U $end
     $var wire  8 =! buffer(0) [7:0] $end
     $var wire  8 >! buffer(1) [7:0] $end
     $var wire  8 G! buffer(10) [7:0] $end
     $var wire  8 H! buffer(11) [7:0] $end
     $var wire  8 I! buffer(12) [7:0] $end
     $var wire  8 J! buffer(13) [7:0] $end
     $var wire  8 K! buffer(14) [7:0] $end
     $var wire  8 L! buffer(15) [7:0] $end
     $var wire  8 M! buffer(16) [7:0] $end
     $var wire  8 N! buffer(17) [7:0] $end
     $var wire  8 O! buffer(18) [7:0] $end
     $var wire  8 P! buffer(19) [7:0] $end
     $var wire  8 ?! buffer(2) [7:0] $end
     $var wire  8 Q! buffer(20) [7:0] $end
     $var wire  8 R! buffer(21) [7:0] $end
     $var wire  8 S! buffer(22) [7:0] $end
     $var wire  8 T! buffer(23) [7:0] $end
     $var wire  8 U! buffer(24) [7:0] $end
     $var wire  8 V! buffer(25) [7:0] $end
     $var wire  8 W! buffer(26) [7:0] $end
     $var wire  8 X! buffer(27) [7:0] $end
     $var wire  8 @! buffer(3) [7:0] $end
     $var wire  8 A! buffer(4) [7:0] $end
     $var wire  8 B! buffer(5) [7:0] $end
     $var wire  8 C! buffer(6) [7:0] $end
     $var wire  8 D! buffer(7) [7:0] $end
     $var wire  8 E! buffer(8) [7:0] $end
     $var wire  8 F! buffer(9) [7:0] $end
     $var wire  1 %" clkr $end
     $var wire  1 %" clkw $end
     $var wire  8 ~! din [7:0] $end
     $var wire  8 <! dout [7:0] $end
     $var wire  1 )" r_en $end
     $var wire  5 #" raddr [4:0] $end
     $var wire  1 (" w_en $end
     $var wire  5 "" waddr [4:0] $end
    $upscope $end
   $upscope $end
   $scope module genblk2(4) $end
    $scope module graylinebuffer_U $end
     $var wire  8 Z! buffer(0) [7:0] $end
     $var wire  8 [! buffer(1) [7:0] $end
     $var wire  8 d! buffer(10) [7:0] $end
     $var wire  8 e! buffer(11) [7:0] $end
     $var wire  8 f! buffer(12) [7:0] $end
     $var wire  8 g! buffer(13) [7:0] $end
     $var wire  8 h! buffer(14) [7:0] $end
     $var wire  8 i! buffer(15) [7:0] $end
     $var wire  8 j! buffer(16) [7:0] $end
     $var wire  8 k! buffer(17) [7:0] $end
     $var wire  8 l! buffer(18) [7:0] $end
     $var wire  8 m! buffer(19) [7:0] $end
     $var wire  8 \! buffer(2) [7:0] $end
     $var wire  8 n! buffer(20) [7:0] $end
     $var wire  8 o! buffer(21) [7:0] $end
     $var wire  8 p! buffer(22) [7:0] $end
     $var wire  8 q! buffer(23) [7:0] $end
     $var wire  8 r! buffer(24) [7:0] $end
     $var wire  8 s! buffer(25) [7:0] $end
     $var wire  8 t! buffer(26) [7:0] $end
     $var wire  8 u! buffer(27) [7:0] $end
     $var wire  8 ]! buffer(3) [7:0] $end
     $var wire  8 ^! buffer(4) [7:0] $end
     $var wire  8 _! buffer(5) [7:0] $end
     $var wire  8 `! buffer(6) [7:0] $end
     $var wire  8 a! buffer(7) [7:0] $end
     $var wire  8 b! buffer(8) [7:0] $end
     $var wire  8 c! buffer(9) [7:0] $end
     $var wire  1 %" clkr $end
     $var wire  1 %" clkw $end
     $var wire  8 !" din [7:0] $end
     $var wire  8 Y! dout [7:0] $end
     $var wire  1 )" r_en $end
     $var wire  5 #" raddr [4:0] $end
     $var wire  1 (" w_en $end
     $var wire  5 "" waddr [4:0] $end
    $upscope $end
   $upscope $end
  $upscope $end
 $upscope $end
$enddefinitions $end


#0
b00000000 #
b00000000 $
b00000000 %
b00000000 &
b00000000 '
b00000000 (
b00000000 )
b00000000 *
b00000000 +
b00000000 ,
b00000000 -
b00000000 .
b00000000 /
b00000000 0
b00000000 1
b00000000 2
b00000000 3
b00000000 4
b00000000 5
b00000000 6
b00000000 7
b00000000 8
b00000000 9
b00000000 :
b00000000 ;
b00000000000000000000000000000000 <
b00000000000000000000000000000000 =
b00000000 >
b00000000 ?
b00000000 @
b00000000 A
b00000000 B
b00000000 C
b00000000 D
b00000000 E
b00000000 F
b00000000 G
b00000000 H
b00000000 I
b00000000 J
b00000000 K
b00000000 L
b00000000 M
b00000000 N
b00000000 O
b00000000 P
b00000000 Q
b00000000 R
b00000000 S
b00000000 T
b00000000 U
b00000000 V
b00000000 W
b00000000 X
b00000000 Y
b00000000 Z
b00000000 [
b00000000 \
b00000000 ]
b00000000 ^
b00000000 _
b00000000 `
b00000000 a
b00000000 b
b00000000 c
b00000000 d
b00000000 e
b00000000 f
b00000000 g
b00000000 h
b00000000 i
b00000000 j
b00000000 k
b00000000 l
b00000000 m
b00000000 n
b00000000 o
b00000000 p
b00000000 q
b00000000 r
b00000000 s
b00000000 t
b00000000 u
b00000000 v
b00000000 w
b00000000 x
b00000000 y
b00000000 z
b00000000 {
b00000000 |
b00000000 }
b00000000 ~
b00000000 !!
b00000000 "!
b00000000 #!
b00000000 $!
b00000000 %!
b00000000 &!
b00000000 '!
b00000000 (!
b00000000 )!
b00000000 *!
b00000000 +!
b00000000 ,!
b00000000 -!
b00000000 .!
b00000000 /!
b00000000 0!
b00000000 1!
b00000000 2!
b00000000 3!
b00000000 4!
b00000000 5!
b00000000 6!
b00000000 7!
b00000000 8!
b00000000 9!
b00000000 :!
b00000000 ;!
b00000000 <!
b00000000 =!
b00000000 >!
b00000000 ?!
b00000000 @!
b00000000 A!
b00000000 B!
b00000000 C!
b00000000 D!
b00000000 E!
b00000000 F!
b00000000 G!
b00000000 H!
b00000000 I!
b00000000 J!
b00000000 K!
b00000000 L!
b00000000 M!
b00000000 N!
b00000000 O!
b00000000 P!
b00000000 Q!
b00000000 R!
b00000000 S!
b00000000 T!
b00000000 U!
b00000000 V!
b00000000 W!
b00000000 X!
b00000000 Y!
b00000000 Z!
b00000000 [!
b00000000 \!
b00000000 ]!
b00000000 ^!
b00000000 _!
b00000000 `!
b00000000 a!
b00000000 b!
b00000000 c!
b00000000 d!
b00000000 e!
b00000000 f!
b00000000 g!
b00000000 h!
b00000000 i!
b00000000 j!
b00000000 k!
b00000000 l!
b00000000 m!
b00000000 n!
b00000000 o!
b00000000 p!
b00000000 q!
b00000000 r!
b00000000 s!
b00000000 t!
b00000000 u!
b00000000 v!
b00000000 w!
b00000000 x!
b00000000 y!
b00000000 z!
b00000000 {!
b00000000 |!
b00000000 }!
b00000000 ~!
b00000000 !"
b00000 ""
b00000 #"
b00010 $"
0%"
0&"
b00000000 '"
0("
1)"
#1
b00000000000000000000000000000101 <
b00000000000000000000000000000101 =
1%"
1("
#2
0%"
1&"
#3
b00001 ""
b00010 #"
b00011 $"
1%"
#4
0%"
#5
b00000001 #
b00000001 E
b00000001 v!
b00000001 {!
b00010 ""
b00011 #"
b00100 $"
1%"
b00000001 '"
#6
0%"
#7
b00000010 #
b00000001 $
b00000010 F
b00000010 v!
b00000010 {!
b00011 ""
b00100 #"
b00101 $"
1%"
b00000010 '"
#8
0%"
#9
b00000011 #
b00000010 $
b00000001 %
b00000011 G
b00000011 v!
b00000011 {!
b00100 ""
b00101 #"
b00110 $"
1%"
b00000011 '"
#10
0%"
#11
b00000100 #
b00000011 $
b00000010 %
b00000001 &
b00000100 H
b00000100 v!
b00000100 {!
b00101 ""
b00110 #"
b00111 $"
1%"
b00000100 '"
#12
0%"
#13
b00000101 #
b00000100 $
b00000011 %
b00000010 &
b00000001 '
b00000101 I
b00000101 v!
b00000101 {!
b00110 ""
b00111 #"
b01000 $"
1%"
b00000101 '"
#14
0%"
#15
b00000110 #
b00000101 $
b00000100 %
b00000011 &
b00000010 '
b00000110 J
b00000110 v!
b00000110 {!
b00111 ""
b01000 #"
b01001 $"
1%"
b00000110 '"
#16
0%"
#17
b00000111 #
b00000110 $
b00000101 %
b00000100 &
b00000011 '
b00000111 K
b00000111 v!
b00000111 {!
b01000 ""
b01001 #"
b01010 $"
1%"
b00000111 '"
#18
0%"
#19
b00001000 #
b00000111 $
b00000110 %
b00000101 &
b00000100 '
b00001000 L
b00001000 v!
b00001000 {!
b01001 ""
b01010 #"
b01011 $"
1%"
b00001000 '"
#20
0%"
#21
b00001001 #
b00001000 $
b00000111 %
b00000110 &
b00000101 '
b00001001 M
b00001001 v!
b00001001 {!
b01010 ""
b01011 #"
b01100 $"
1%"
b00001001 '"
#22
0%"
#23
b00001010 #
b00001001 $
b00001000 %
b00000111 &
b00000110 '
b00001010 N
b00001010 v!
b00001010 {!
b01011 ""
b01100 #"
b01101 $"
1%"
b00001010 '"
#24
0%"
#25
b00001011 #
b00001010 $
b00001001 %
b00001000 &
b00000111 '
b00001011 O
b00001011 v!
b00001011 {!
b01100 ""
b01101 #"
b01110 $"
1%"
b00001011 '"
#26
0%"
#27
b00001100 #
b00001011 $
b00001010 %
b00001001 &
b00001000 '
b00001100 P
b00001100 v!
b00001100 {!
b01101 ""
b01110 #"
b01111 $"
1%"
b00001100 '"
#28
0%"
#29
b00001101 #
b00001100 $
b00001011 %
b00001010 &
b00001001 '
b00001101 Q
b00001101 v!
b00001101 {!
b01110 ""
b01111 #"
b10000 $"
1%"
b00001101 '"
#30
0%"
#31
b00001110 #
b00001101 $
b00001100 %
b00001011 &
b00001010 '
b00001110 R
b00001110 v!
b00001110 {!
b01111 ""
b10000 #"
b10001 $"
1%"
b00001110 '"
#32
0%"
#33
b00001111 #
b00001110 $
b00001101 %
b00001100 &
b00001011 '
b00001111 S
b00001111 v!
b00001111 {!
b10000 ""
b10001 #"
b10010 $"
1%"
b00001111 '"
#34
0%"
#35
b00010000 #
b00001111 $
b00001110 %
b00001101 &
b00001100 '
b00010000 T
b00010000 v!
b00010000 {!
b10001 ""
b10010 #"
b10011 $"
1%"
b00010000 '"
#36
0%"
#37
b00010001 #
b00010000 $
b00001111 %
b00001110 &
b00001101 '
b00010001 U
b00010001 v!
b00010001 {!
b10010 ""
b10011 #"
b10100 $"
1%"
b00010001 '"
#38
0%"
#39
b00010010 #
b00010001 $
b00010000 %
b00001111 &
b00001110 '
b00010010 V
b00010010 v!
b00010010 {!
b10011 ""
b10100 #"
b10101 $"
1%"
b00010010 '"
#40
0%"
#41
b00010011 #
b00010010 $
b00010001 %
b00010000 &
b00001111 '
b00010011 W
b00010011 v!
b00010011 {!
b10100 ""
b10101 #"
b10110 $"
1%"
b00010011 '"
#42
0%"
#43
b00010100 #
b00010011 $
b00010010 %
b00010001 &
b00010000 '
b00010100 X
b00010100 v!
b00010100 {!
b10101 ""
b10110 #"
b10111 $"
1%"
b00010100 '"
#44
0%"
#45
b00010101 #
b00010100 $
b00010011 %
b00010010 &
b00010001 '
b00010101 Y
b00010101 v!
b00010101 {!
b10110 ""
b10111 #"
b11000 $"
1%"
b00010101 '"
#46
0%"
#47
b00010110 #
b00010101 $
b00010100 %
b00010011 &
b00010010 '
b00010110 Z
b00010110 v!
b00010110 {!
b10111 ""
b11000 #"
b11001 $"
1%"
b00010110 '"
#48
0%"
#49
b00010111 #
b00010110 $
b00010101 %
b00010100 &
b00010011 '
b00010111 [
b00010111 v!
b00010111 {!
b11000 ""
b11001 #"
b11010 $"
1%"
b00010111 '"
#50
0%"
#51
b00011000 #
b00010111 $
b00010110 %
b00010101 &
b00010100 '
b00011000 \
b00011000 v!
b00011000 {!
b11001 ""
b11010 #"
b11011 $"
1%"
b00011000 '"
#52
0%"
#53
b00011001 #
b00011000 $
b00010111 %
b00010110 &
b00010101 '
b00011001 ]
b00011001 v!
b00011001 {!
b11010 ""
b11011 #"
b11100 $"
1%"
b00011001 '"
#54
0%"
#55
b00011010 #
b00011001 $
b00011000 %
b00010111 &
b00010110 '
b00011010 ^
b00011010 v!
b00011010 {!
b11011 ""
b00000 #"
b11101 $"
1%"
b00011010 '"
#56
0%"
#57
b00011011 #
b00011010 $
b00011001 %
b00011000 &
b00010111 '
b00011011 _
b00011011 v!
b00011011 {!
b00000 ""
b00001 #"
b00010 $"
1%"
b00011011 '"
#58
0%"
#59
b00011100 #
b00011011 $
b00011010 %
b00011001 &
b00011000 '
b00000001 >
b00000001 C
b00011100 D
b00011100 v!
b00000001 w!
b00011100 {!
b00000001 |!
b00001 ""
b00010 #"
b00011 $"
1%"
b00011100 '"
#60
0%"
#61
b00011101 #
b00011100 $
b00011011 %
b00011010 &
b00011001 '
b00000001 (
b00000010 >
b00000010 C
b00011101 E
b00000001 b
b00011101 v!
b00000010 w!
b00011101 {!
b00000010 |!
b00010 ""
b00011 #"
b00100 $"
1%"
b00011101 '"
#62
0%"
#63
b00011110 #
b00011101 $
b00011100 %
b00011011 &
b00011010 '
b00000010 (
b00000001 )
b00000011 >
b00000011 C
b00011110 F
b00000010 c
b00011110 v!
b00000011 w!
b00011110 {!
b00000011 |!
b00011 ""
b00100 #"
b00101 $"
1%"
b00011110 '"
#64
0%"
#65
b00011111 #
b00011110 $
b00011101 %
b00011100 &
b00011011 '
b00000011 (
b00000010 )
b00000001 *
b00000100 >
b00000100 C
b00011111 G
b00000011 d
b00011111 v!
b00000100 w!
b00011111 {!
b00000100 |!
b00100 ""
b00101 #"
b00110 $"
1%"
b00011111 '"
#66
0%"
#67
b00100000 #
b00011111 $
b00011110 %
b00011101 &
b00011100 '
b00000100 (
b00000011 )
b00000010 *
b00000001 +
b00000101 >
b00000101 C
b00100000 H
b00000100 e
b00100000 v!
b00000101 w!
b00100000 {!
b00000101 |!
b00101 ""
b00110 #"
b00111 $"
1%"
b00100000 '"
#68
0%"
#69
b00100001 #
b00100000 $
b00011111 %
b00011110 &
b00011101 '
b00000101 (
b00000100 )
b00000011 *
b00000010 +
b00000001 ,
b00000110 >
b00000110 C
b00100001 I
b00000101 f
b00100001 v!
b00000110 w!
b00100001 {!
b00000110 |!
b00110 ""
b00111 #"
b01000 $"
1%"
b00100001 '"
#70
0%"
#71
b00100010 #
b00100001 $
b00100000 %
b00011111 &
b00011110 '
b00000110 (
b00000101 )
b00000100 *
b00000011 +
b00000010 ,
b00000111 >
b00000111 C
b00100010 J
b00000110 g
b00100010 v!
b00000111 w!
b00100010 {!
b00000111 |!
b00111 ""
b01000 #"
b01001 $"
1%"
b00100010 '"
#72
0%"
#73
b00100011 #
b00100010 $
b00100001 %
b00100000 &
b00011111 '
b00000111 (
b00000110 )
b00000101 *
b00000100 +
b00000011 ,
b00001000 >
b00001000 C
b00100011 K
b00000111 h
b00100011 v!
b00001000 w!
b00100011 {!
b00001000 |!
b01000 ""
b01001 #"
b01010 $"
1%"
b00100011 '"
#74
0%"
#75
b00100100 #
b00100011 $
b00100010 %
b00100001 &
b00100000 '
b00001000 (
b00000111 )
b00000110 *
b00000101 +
b00000100 ,
b00001001 >
b00001001 C
b00100100 L
b00001000 i
b00100100 v!
b00001001 w!
b00100100 {!
b00001001 |!
b01001 ""
b01010 #"
b01011 $"
1%"
b00100100 '"
#76
0%"
#77
b00100101 #
b00100100 $
b00100011 %
b00100010 &
b00100001 '
b00001001 (
b00001000 )
b00000111 *
b00000110 +
b00000101 ,
b00001010 >
b00001010 C
b00100101 M
b00001001 j
b00100101 v!
b00001010 w!
b00100101 {!
b00001010 |!
b01010 ""
b01011 #"
b01100 $"
1%"
b00100101 '"
#78
0%"
#79
b00100110 #
b00100101 $
b00100100 %
b00100011 &
b00100010 '
b00001010 (
b00001001 )
b00001000 *
b00000111 +
b00000110 ,
b00001011 >
b00001011 C
b00100110 N
b00001010 k
b00100110 v!
b00001011 w!
b00100110 {!
b00001011 |!
b01011 ""
b01100 #"
b01101 $"
1%"
b00100110 '"
#80
0%"
#81
b00100111 #
b00100110 $
b00100101 %
b00100100 &
b00100011 '
b00001011 (
b00001010 )
b00001001 *
b00001000 +
b00000111 ,
b00001100 >
b00001100 C
b00100111 O
b00001011 l
b00100111 v!
b00001100 w!
b00100111 {!
b00001100 |!
b01100 ""
b01101 #"
b01110 $"
1%"
b00100111 '"
#82
0%"
#83
b00101000 #
b00100111 $
b00100110 %
b00100101 &
b00100100 '
b00001100 (
b00001011 )
b00001010 *
b00001001 +
b00001000 ,
b00001101 >
b00001101 C
b00101000 P
b00001100 m
b00101000 v!
b00001101 w!
b00101000 {!
b00001101 |!
b01101 ""
b01110 #"
b01111 $"
1%"
b00101000 '"
#84
0%"
#85
b00101001 #
b00101000 $
b00100111 %
b00100110 &
b00100101 '
b00001101 (
b00001100 )
b00001011 *
b00001010 +
b00001001 ,
b00001110 >
b00001110 C
b00101001 Q
b00001101 n
b00101001 v!
b00001110 w!
b00101001 {!
b00001110 |!
b01110 ""
b01111 #"
b10000 $"
1%"
b00101001 '"
#86
0%"
#87
b00101010 #
b00101001 $
b00101000 %
b00100111 &
b00100110 '
b00001110 (
b00001101 )
b00001100 *
b00001011 +
b00001010 ,
b00001111 >
b00001111 C
b00101010 R
b00001110 o
b00101010 v!
b00001111 w!
b00101010 {!
b00001111 |!
b01111 ""
b10000 #"
b10001 $"
1%"
b00101010 '"
#88
0%"
#89
b00101011 #
b00101010 $
b00101001 %
b00101000 &
b00100111 '
b00001111 (
b00001110 )
b00001101 *
b00001100 +
b00001011 ,
b00010000 >
b00010000 C
b00101011 S
b00001111 p
b00101011 v!
b00010000 w!
b00101011 {!
b00010000 |!
b10000 ""
b10001 #"
b10010 $"
1%"
b00101011 '"
#90
0%"
#91
b00101100 #
b00101011 $
b00101010 %
b00101001 &
b00101000 '
b00010000 (
b00001111 )
b00001110 *
b00001101 +
b00001100 ,
b00010001 >
b00010001 C
b00101100 T
b00010000 q
b00101100 v!
b00010001 w!
b00101100 {!
b00010001 |!
b10001 ""
b10010 #"
b10011 $"
1%"
b00101100 '"
#92
0%"
#93
b00101101 #
b00101100 $
b00101011 %
b00101010 &
b00101001 '
b00010001 (
b00010000 )
b00001111 *
b00001110 +
b00001101 ,
b00010010 >
b00010010 C
b00101101 U
b00010001 r
b00101101 v!
b00010010 w!
b00101101 {!
b00010010 |!
b10010 ""
b10011 #"
b10100 $"
1%"
b00101101 '"
#94
0%"
#95
b00101110 #
b00101101 $
b00101100 %
b00101011 &
b00101010 '
b00010010 (
b00010001 )
b00010000 *
b00001111 +
b00001110 ,
b00010011 >
b00010011 C
b00101110 V
b00010010 s
b00101110 v!
b00010011 w!
b00101110 {!
b00010011 |!
b10011 ""
b10100 #"
b10101 $"
1%"
b00101110 '"
#96
0%"
#97
b00101111 #
b00101110 $
b00101101 %
b00101100 &
b00101011 '
b00010011 (
b00010010 )
b00010001 *
b00010000 +
b00001111 ,
b00010100 >
b00010100 C
b00101111 W
b00010011 t
b00101111 v!
b00010100 w!
b00101111 {!
b00010100 |!
b10100 ""
b10101 #"
b10110 $"
1%"
b00101111 '"
#98
0%"
