vsrc/cnn_defines.v
`define CNN_DATA_IN_W 8 /* 灰度数据8位 */
`define CNN_GRAY_BUFFER_ADDR_W 5 /* 灰度流缓存器地址宽度 */
`define CNN_IMG_IN_WIDTH 28 /* 输入图像宽 */
`define CNN_CONV1_OUT_W 192 /* 第一层输出6*32 */

conv_para/vsrc/graylinebuffer.v
/* 灰度流缓存 双口ram*/
`include "cnn_defines.v"
module graylinebuffer
#(
    parameter IMG_IN_WIDTH = 28
)
(
    clkw    ,
    w_en    ,
    waddr   ,
    din     ,

    clkr    ,
    r_en    ,
    raddr   ,
    dout
);
    input                                   clkw    ;
    input                                   clkr    ;
    input                                   w_en    ;
    input                                   r_en    ;
    input  [`CNN_GRAY_BUFFER_ADDR_W-1:0]    waddr   ;
    input  [`CNN_GRAY_BUFFER_ADDR_W-1:0]    raddr   ;
    input  [`CNN_DATA_IN_W-1:0]             din     ;

    output reg [`CNN_DATA_IN_W-1:0] dout;

    reg [`CNN_DATA_IN_W-1:0] buffer [IMG_IN_WIDTH-1:0];

    always@(posedge clkw) begin
        if(w_en)
            buffer[waddr] <= din;
        else
            ;
    end

    always@(posedge clkr) begin
        if(r_en)
            dout <= buffer[raddr];
        else
            ;
    end


endmodule

conv1.v
`include "cnn_defines.v"
`include "graylinebuffer.v"
module conv1(
    clk                 ,
    rst_n               ,

    cnn_data_in         ,
    cnn_data_in_valid   /*,

    cnn_data_out        ,
    cnn_data_out_valid*/
);

    input                           clk                 ;
    input                           rst_n               ;
    input   [`CNN_DATA_IN_W-1:0]    cnn_data_in         ;
    input                           cnn_data_in_valid   ;
    /*output  [`CNN_CONV1_OUT_W-1:0]  cnn_data_out        ;
    output reg                      cnn_data_out_valid  ;*/

    /*wire [31:0] data_out_array [5:0];/* 输出6通道 */

    /*======================= addr ============================*/
    reg [4:0]   wr_addr;
    reg [4:0]   rd_addr;
    wire [4:0] rd_addr_pre2 = wr_addr +2;
    always@(posedge clk, negedge rst_n)begin
        if(~rst_n)begin
            wr_addr <= 0;
            rd_addr <= 0;
        end
        else if(cnn_data_in_valid == 1'b1)begin
            //========== A ============
            if(wr_addr == 'd27)
                wr_addr <= 5'd0;
            else
                wr_addr <= wr_addr + 1'd1;
            //========== B ============
            if(rd_addr_pre2 > 'd27)
                rd_addr <= rd_addr_pre2 - 5'd28;
            else
                rd_addr <= rd_addr_pre2;
        end
    end
//======================= data ===============================
    wire    [7:0]   window_in[0:5-1];
    wire    [7:0]   window_out[0:5-1];
    assign  window_in[0]    = cnn_data_in;
    genvar k;
    generate
    for(k=1;k<5;k=k+1)begin
       assign    window_in[k]=window_out[k-1];
    end
    endgenerate
    
    
    //======================= Instance ===============================
    
    generate
    for (k=0;k<5;k=k+1)begin
    graylinebuffer graylinebuffer_U (
        .clkw (clk              ), 
        .w_en (cnn_data_in_valid), 
        .waddr(wr_addr          ), 
        .din  (window_in[k]     ), 
        .clkr (clk              ), 
        .r_en (1'b1             ), 
        .raddr(rd_addr          ), 
        .dout (window_out[k]    ) 
    );
    end
    endgenerate
    //======================= window ===============================
    reg signed [7:0] window[5-1:0][5-1:0];
    integer i,j;
    always@(posedge clk ,negedge rst_n)begin
        if(~rst_n)begin
            for(i=0;i<5;i=i+1)begin
                for(j=0;j<5;j=j+1)begin
                    window[i][j]<=0;
                end
            end
        end
        else if(cnn_data_in_valid == 1'b1 )begin
            for(i=0;i<5;i=i+1)begin
                window[i][0] <= window_in[i];
                for(j=1;j<5;j=j+1)begin
                    window[i][j]<=window[i][j-1];
                end
            end
        end
    end
endmodule

waveform.vcd
$version Generated by VerilatedVcd $end
$date Sun Mar  5 22:17:27 2023 $end
$timescale 1ps $end

 $scope module TOP $end
  $var wire  1 %" clk $end
  $var wire  8 '" cnn_data_in [7:0] $end
  $var wire  1 (" cnn_data_in_valid $end
  $var wire  1 &" rst_n $end
  $scope module conv1 $end
   $var wire  1 %" clk $end
   $var wire  8 '" cnn_data_in [7:0] $end
   $var wire  1 (" cnn_data_in_valid $end
   $var wire 32 < i [31:0] $end
   $var wire 32 = j [31:0] $end
   $var wire  5 #" rd_addr [4:0] $end
   $var wire  5 $" rd_addr_pre2 [4:0] $end
   $var wire  1 &" rst_n $end
   $var wire  8 # window(0)(0) [7:0] $end
   $var wire  8 $ window(0)(1) [7:0] $end
   $var wire  8 % window(0)(2) [7:0] $end
   $var wire  8 & window(0)(3) [7:0] $end
   $var wire  8 ' window(0)(4) [7:0] $end
   $var wire  8 ( window(1)(0) [7:0] $end
   $var wire  8 ) window(1)(1) [7:0] $end
   $var wire  8 * window(1)(2) [7:0] $end
   $var wire  8 + window(1)(3) [7:0] $end
   $var wire  8 , window(1)(4) [7:0] $end
   $var wire  8 - window(2)(0) [7:0] $end
   $var wire  8 . window(2)(1) [7:0] $end
   $var wire  8 / window(2)(2) [7:0] $end
   $var wire  8 0 window(2)(3) [7:0] $end
   $var wire  8 1 window(2)(4) [7:0] $end
   $var wire  8 2 window(3)(0) [7:0] $end
   $var wire  8 3 window(3)(1) [7:0] $end
   $var wire  8 4 window(3)(2) [7:0] $end
   $var wire  8 5 window(3)(3) [7:0] $end
   $var wire  8 6 window(3)(4) [7:0] $end
   $var wire  8 7 window(4)(0) [7:0] $end
   $var wire  8 8 window(4)(1) [7:0] $end
   $var wire  8 9 window(4)(2) [7:0] $end
   $var wire  8 : window(4)(3) [7:0] $end
   $var wire  8 ; window(4)(4) [7:0] $end
   $var wire  8 v! window_in(0) [7:0] $end
   $var wire  8 w! window_in(1) [7:0] $end
   $var wire  8 x! window_in(2) [7:0] $end
   $var wire  8 y! window_in(3) [7:0] $end
   $var wire  8 z! window_in(4) [7:0] $end
   $var wire  8 > window_out(0) [7:0] $end
   $var wire  8 ? window_out(1) [7:0] $end
   $var wire  8 @ window_out(2) [7:0] $end
   $var wire  8 A window_out(3) [7:0] $end
   $var wire  8 B window_out(4) [7:0] $end
   $var wire  5 "" wr_addr [4:0] $end
   $scope module genblk2(0) $end
    $scope module graylinebuffer_U $end
     $var wire  8 D buffer(0) [7:0] $end
     $var wire  8 E buffer(1) [7:0] $end
     $var wire  8 N buffer(10) [7:0] $end
     $var wire  8 O buffer(11) [7:0] $end
     $var wire  8 P buffer(12) [7:0] $end
     $var wire  8 Q buffer(13) [7:0] $end
     $var wire  8 R buffer(14) [7:0] $end
     $var wire  8 S buffer(15) [7:0] $end
     $var wire  8 T buffer(16) [7:0] $end
     $var wire  8 U buffer(17) [7:0] $end
     $var wire  8 V buffer(18) [7:0] $end
     $var wire  8 W buffer(19) [7:0] $end
     $var wire  8 F buffer(2) [7:0] $end
     $var wire  8 X buffer(20) [7:0] $end
     $var wire  8 Y buffer(21) [7:0] $end
     $var wire  8 Z buffer(22) [7:0] $end
     $var wire  8 [ buffer(23) [7:0] $end
     $var wire  8 \ buffer(24) [7:0] $end
     $var wire  8 ] buffer(25) [7:0] $end
     $var wire  8 ^ buffer(26) [7:0] $end
     $var wire  8 _ buffer(27) [7:0] $end
     $var wire  8 G buffer(3) [7:0] $end
     $var wire  8 H buffer(4) [7:0] $end
     $var wire  8 I buffer(5) [7:0] $end
     $var wire  8 J buffer(6) [7:0] $end
     $var wire  8 K buffer(7) [7:0] $end
     $var wire  8 L buffer(8) [7:0] $end
     $var wire  8 M buffer(9) [7:0] $end
     $var wire  1 %" clkr $end
     $var wire  1 %" clkw $end
     $var wire  8 {! din [7:0] $end
     $var wire  8 C dout [7:0] $end
     $var wire  1 )" r_en $end
     $var wire  5 #" raddr [4:0] $end
     $var wire  1 (" w_en $end
     $var wire  5 "" waddr [4:0] $end
    $upscope $end
   $upscope $end
   $scope module genblk2(1) $end
    $scope module graylinebuffer_U $end
     $var wire  8 a buffer(0) [7:0] $end
     $var wire  8 b buffer(1) [7:0] $end
     $var wire  8 k buffer(10) [7:0] $end
     $var wire  8 l buffer(11) [7:0] $end
     $var wire  8 m buffer(12) [7:0] $end
     $var wire  8 n buffer(13) [7:0] $end
     $var wire  8 o buffer(14) [7:0] $end
     $var wire  8 p buffer(15) [7:0] $end
     $var wire  8 q buffer(16) [7:0] $end
     $var wire  8 r buffer(17) [7:0] $end
     $var wire  8 s buffer(18) [7:0] $end
     $var wire  8 t buffer(19) [7:0] $end
     $var wire  8 c buffer(2) [7:0] $end
     $var wire  8 u buffer(20) [7:0] $end
     $var wire  8 v buffer(21) [7:0] $end
     $var wire  8 w buffer(22) [7:0] $end
     $var wire  8 x buffer(23) [7:0] $end
     $var wire  8 y buffer(24) [7:0] $end
     $var wire  8 z buffer(25) [7:0] $end
     $var wire  8 { buffer(26) [7:0] $end
     $var wire  8 | buffer(27) [7:0] $end
     $var wire  8 d buffer(3) [7:0] $end
     $var wire  8 e buffer(4) [7:0] $end
     $var wire  8 f buffer(5) [7:0] $end
     $var wire  8 g buffer(6) [7:0] $end
     $var wire  8 h buffer(7) [7:0] $end
     $var wire  8 i buffer(8) [7:0] $end
     $var wire  8 j buffer(9) [7:0] $end
     $var wire  1 %" clkr $end
     $var wire  1 %" clkw $end
     $var wire  8 |! din [7:0] $end
     $var wire  8 ` dout [7:0] $end
     $var wire  1 )" r_en $end
     $var wire  5 #" raddr [4:0] $end
     $var wire  1 (" w_en $end
     $var wire  5 "" waddr [4:0] $end
    $upscope $end
   $upscope $end
   $scope module genblk2(2) $end
    $scope module graylinebuffer_U $end
     $var wire  8 ~ buffer(0) [7:0] $end
     $var wire  8 !! buffer(1) [7:0] $end
     $var wire  8 *! buffer(10) [7:0] $end
     $var wire  8 +! buffer(11) [7:0] $end
     $var wire  8 ,! buffer(12) [7:0] $end
     $var wire  8 -! buffer(13) [7:0] $end
     $var wire  8 .! buffer(14) [7:0] $end
     $var wire  8 /! buffer(15) [7:0] $end
     $var wire  8 0! buffer(16) [7:0] $end
     $var wire  8 1! buffer(17) [7:0] $end
     $var wire  8 2! buffer(18) [7:0] $end
     $var wire  8 3! buffer(19) [7:0] $end
     $var wire  8 "! buffer(2) [7:0] $end
     $var wire  8 4! buffer(20) [7:0] $end
     $var wire  8 5! buffer(21) [7:0] $end
     $var wire  8 6! buffer(22) [7:0] $end
     $var wire  8 7! buffer(23) [7:0] $end
     $var wire  8 8! buffer(24) [7:0] $end
     $var wire  8 9! buffer(25) [7:0] $end
     $var wire  8 :! buffer(26) [7:0] $end
     $var wire  8 ;! buffer(27) [7:0] $end
     $var wire  8 #! buffer(3) [7:0] $end
     $var wire  8 $! buffer(4) [7:0] $end
     $var wire  8 %! buffer(5) [7:0] $end
     $var wire  8 &! buffer(6) [7:0] $end
     $var wire  8 '! buffer(7) [7:0] $end
     $var wire  8 (! buffer(8) [7:0] $end
     $var wire  8 )! buffer(9) [7:0] $end
     $var wire  1 %" clkr $end
     $var wire  1 %" clkw $end
     $var wire  8 }! din [7:0] $end
     $var wire  8 } dout [7:0] $end
     $var wire  1 )" r_en $end
     $var wire  5 #" raddr [4:0] $end
     $var wire  1 (" w_en $end
     $var wire  5 "" waddr [4:0] $end
    $upscope $end
   $upscope $end
   $scope module genblk2(3) $end
    $scope module graylinebuffer_U $end
     $var wire  8 =! buffer(0) [7:0] $end
     $var wire  8 >! buffer(1) [7:0] $end
     $var wire  8 G! buffer(10) [7:0] $end
     $var wire  8 H! buffer(11) [7:0] $end
     $var wire  8 I! buffer(12) [7:0] $end
     $var wire  8 J! buffer(13) [7:0] $end
     $var wire  8 K! buffer(14) [7:0] $end
     $var wire  8 L! buffer(15) [7:0] $end
     $var wire  8 M! buffer(16) [7:0] $end
     $var wire  8 N! buffer(17) [7:0] $end
     $var wire  8 O! buffer(18) [7:0] $end
     $var wire  8 P! buffer(19) [7:0] $end
     $var wire  8 ?! buffer(2) [7:0] $end
     $var wire  8 Q! buffer(20) [7:0] $end
     $var wire  8 R! buffer(21) [7:0] $end
     $var wire  8 S! buffer(22) [7:0] $end
     $var wire  8 T! buffer(23) [7:0] $end
     $var wire  8 U! buffer(24) [7:0] $end
     $var wire  8 V! buffer(25) [7:0] $end
     $var wire  8 W! buffer(26) [7:0] $end
     $var wire  8 X! buffer(27) [7:0] $end
     $var wire  8 @! buffer(3) [7:0] $end
     $var wire  8 A! buffer(4) [7:0] $end
     $var wire  8 B! buffer(5) [7:0] $end
     $var wire  8 C! buffer(6) [7:0] $end
     $var wire  8 D! buffer(7) [7:0] $end
     $var wire  8 E! buffer(8) [7:0] $end
     $var wire  8 F! buffer(9) [7:0] $end
     $var wire  1 %" clkr $end
     $var wire  1 %" clkw $end
     $var wire  8 ~! din [7:0] $end
     $var wire  8 <! dout [7:0] $end
     $var wire  1 )" r_en $end
     $var wire  5 #" raddr [4:0] $end
     $var wire  1 (" w_en $end
     $var wire  5 "" waddr [4:0] $end
    $upscope $end
   $upscope $end
   $scope module genblk2(4) $end
    $scope module graylinebuffer_U $end
     $var wire  8 Z! buffer(0) [7:0] $end
     $var wire  8 [! buffer(1) [7:0] $end
     $var wire  8 d! buffer(10) [7:0] $end
     $var wire  8 e! buffer(11) [7:0] $end
     $var wire  8 f! buffer(12) [7:0] $end
     $var wire  8 g! buffer(13) [7:0] $end
     $var wire  8 h! buffer(14) [7:0] $end
     $var wire  8 i! buffer(15) [7:0] $end
     $var wire  8 j! buffer(16) [7:0] $end
     $var wire  8 k! buffer(17) [7:0] $end
     $var wire  8 l! buffer(18) [7:0] $end
     $var wire  8 m! buffer(19) [7:0] $end
     $var wire  8 \! buffer(2) [7:0] $end
     $var wire  8 n! buffer(20) [7:0] $end
     $var wire  8 o! buffer(21) [7:0] $end
     $var wire  8 p! buffer(22) [7:0] $end
     $var wire  8 q! buffer(23) [7:0] $end
     $var wire  8 r! buffer(24) [7:0] $end
     $var wire  8 s! buffer(25) [7:0] $end
     $var wire  8 t! buffer(26) [7:0] $end
     $var wire  8 u! buffer(27) [7:0] $end
     $var wire  8 ]! buffer(3) [7:0] $end
     $var wire  8 ^! buffer(4) [7:0] $end
     $var wire  8 _! buffer(5) [7:0] $end
     $var wire  8 `! buffer(6) [7:0] $end
     $var wire  8 a! buffer(7) [7:0] $end
     $var wire  8 b! buffer(8) [7:0] $end
     $var wire  8 c! buffer(9) [7:0] $end
     $var wire  1 %" clkr $end
     $var wire  1 %" clkw $end
     $var wire  8 !" din [7:0] $end
     $var wire  8 Y! dout [7:0] $end
     $var wire  1 )" r_en $end
     $var wire  5 #" raddr [4:0] $end
     $var wire  1 (" w_en $end
     $var wire  5 "" waddr [4:0] $end
    $upscope $end
   $upscope $end
  $upscope $end
 $upscope $end
$enddefinitions $end


#0
b00000000 #
b00000000 $
b00000000 %
b00000000 &
b00000000 '
b00000000 (
b00000000 )
b00000000 *
b00000000 +
b00000000 ,
b00000000 -
b00000000 .
b00000000 /
b00000000 0
b00000000 1
b00000000 2
b00000000 3
b00000000 4
b00000000 5
b00000000 6
b00000000 7
b00000000 8
b00000000 9
b00000000 :
b00000000 ;
b00000000000000000000000000000000 <
b00000000000000000000000000000000 =
b00000000 >
b00000000 ?
b00000000 @
b00000000 A
b00000000 B
b00000000 C
b00000000 D
b00000000 E
b00000000 F
b00000000 G
b00000000 H
b00000000 I
b00000000 J
b00000000 K
b00000000 L
b00000000 M
b00000000 N
b00000000 O
b00000000 P
b00000000 Q
b00000000 R
b00000000 S
b00000000 T
b00000000 U
b00000000 V
b00000000 W
b00000000 X
b00000000 Y
b00000000 Z
b00000000 [
b00000000 \
b00000000 ]
b00000000 ^
b00000000 _
b00000000 `
b00000000 a
b00000000 b
b00000000 c
b00000000 d
b00000000 e
b00000000 f
b00000000 g
b00000000 h
b00000000 i
b00000000 j
b00000000 k
b00000000 l
b00000000 m
b00000000 n
b00000000 o
b00000000 p
b00000000 q
b00000000 r
b00000000 s
b00000000 t
b00000000 u
b00000000 v
b00000000 w
b00000000 x
b00000000 y
b00000000 z
b00000000 {
b00000000 |
b00000000 }
b00000000 ~
b00000000 !!
b00000000 "!
b00000000 #!
b00000000 $!
b00000000 %!
b00000000 &!
b00000000 '!
b00000000 (!
b00000000 )!
b00000000 *!
b00000000 +!
b00000000 ,!
b00000000 -!
b00000000 .!
b00000000 /!
b00000000 0!
b00000000 1!
b00000000 2!
b00000000 3!
b00000000 4!
b00000000 5!
b00000000 6!
b00000000 7!
b00000000 8!
b00000000 9!
b00000000 :!
b00000000 ;!
b00000000 <!
b00000000 =!
b00000000 >!
b00000000 ?!
b00000000 @!
b00000000 A!
b00000000 B!
b00000000 C!
b00000000 D!
b00000000 E!
b00000000 F!
b00000000 G!
b00000000 H!
b00000000 I!
b00000000 J!
b00000000 K!
b00000000 L!
b00000000 M!
b00000000 N!
b00000000 O!
b00000000 P!
b00000000 Q!
b00000000 R!
b00000000 S!
b00000000 T!
b00000000 U!
b00000000 V!
b00000000 W!
b00000000 X!
b00000000 Y!
b00000000 Z!
b00000000 [!
b00000000 \!
b00000000 ]!
b00000000 ^!
b00000000 _!
b00000000 `!
b00000000 a!
b00000000 b!
b00000000 c!
b00000000 d!
b00000000 e!
b00000000 f!
b00000000 g!
b00000000 h!
b00000000 i!
b00000000 j!
b00000000 k!
b00000000 l!
b00000000 m!
b00000000 n!
b00000000 o!
b00000000 p!
b00000000 q!
b00000000 r!
b00000000 s!
b00000000 t!
b00000000 u!
b00000000 v!
b00000000 w!
b00000000 x!
b00000000 y!
b00000000 z!
b00000000 {!
b00000000 |!
b00000000 }!
b00000000 ~!
b00000000 !"
b00000 ""
b00000 #"
b00010 $"
0%"
0&"
b00000000 '"
0("
1)"
#1
b00000000000000000000000000000101 <
b00000000000000000000000000000101 =
1%"
1("
#2
0%"
1&"
#3
b00001 ""
b00010 #"
b00011 $"
1%"
#4
0%"
#5
b00010 ""
b00011 #"
b00100 $"
1%"
#6
0%"
#7
b00011 ""
b00100 #"
b00101 $"
1%"
#8
0%"
#9
b00100 ""
b00101 #"
b00110 $"
1%"
#10
0%"
#11
b00101 ""
b00110 #"
b00111 $"
1%"
#12
0%"
#13
b00110 ""
b00111 #"
b01000 $"
1%"
#14
0%"
#15
b00111 ""
b01000 #"
b01001 $"
1%"
#16
0%"
#17
b01000 ""
b01001 #"
b01010 $"
1%"
#18
0%"
#19
b01001 ""
b01010 #"
b01011 $"
1%"
#20
0%"
#21
b01010 ""
b01011 #"
b01100 $"
1%"
#22
0%"
#23
b01011 ""
b01100 #"
b01101 $"
1%"
#24
0%"
#25
b01100 ""
b01101 #"
b01110 $"
1%"
#26
0%"
#27
b01101 ""
b01110 #"
b01111 $"
1%"
#28
0%"
#29
b01110 ""
b01111 #"
b10000 $"
1%"
#30
0%"
#31
b01111 ""
b10000 #"
b10001 $"
1%"
#32
0%"
#33
b10000 ""
b10001 #"
b10010 $"
1%"
#34
0%"
#35
b10001 ""
b10010 #"
b10011 $"
1%"
#36
0%"
#37
b10010 ""
b10011 #"
b10100 $"
1%"
#38
0%"
#39
b10011 ""
b10100 #"
b10101 $"
1%"
#40
0%"
#41
b10100 ""
b10101 #"
b10110 $"
1%"
#42
0%"
#43
b10101 ""
b10110 #"
b10111 $"
1%"
#44
0%"
#45
b10110 ""
b10111 #"
b11000 $"
1%"
#46
0%"
#47
b10111 ""
b11000 #"
b11001 $"
1%"
#48
0%"
#49
b11000 ""
b11001 #"
b11010 $"
1%"
#50
0%"
#51
b11001 ""
b11010 #"
b11011 $"
1%"
#52
0%"
#53
b11010 ""
b11011 #"
b11100 $"
1%"
#54
0%"
#55
b11011 ""
b00000 #"
b11101 $"
1%"
#56
0%"
#57
b00000 ""
b00001 #"
b00010 $"
1%"
#58
0%"
#59
b00001 ""
b00010 #"
b00011 $"
1%"
#60
0%"
#61
b00010 ""
b00011 #"
b00100 $"
1%"
#62
0%"
#63
b00011 ""
b00100 #"
b00101 $"
1%"
#64
0%"
#65
b00100 ""
b00101 #"
b00110 $"
1%"
#66
0%"
#67
b00101 ""
b00110 #"
b00111 $"
1%"
#68
0%"
#69
b00110 ""
b00111 #"
b01000 $"
1%"
#70
0%"
#71
b00111 ""
b01000 #"
b01001 $"
1%"
#72
0%"
#73
b01000 ""
b01001 #"
b01010 $"
1%"
#74
0%"
#75
b01001 ""
b01010 #"
b01011 $"
1%"
#76
0%"
#77
b01010 ""
b01011 #"
b01100 $"
1%"
#78
0%"
#79
b01011 ""
b01100 #"
b01101 $"
1%"
#80
0%"
#81
b01100 ""
b01101 #"
b01110 $"
1%"
#82
0%"
#83
b01101 ""
b01110 #"
b01111 $"
1%"
#84
0%"
#85
b01110 ""
b01111 #"
b10000 $"
1%"
#86
0%"
#87
b01111 ""
b10000 #"
b10001 $"
1%"
#88
0%"
#89
b10000 ""
b10001 #"
b10010 $"
1%"
#90
0%"
#91
b10001 ""
b10010 #"
b10011 $"
1%"
#92
0%"
#93
b10010 ""
b10011 #"
b10100 $"
1%"
#94
0%"
#95
b10011 ""
b10100 #"
b10101 $"
1%"
#96
0%"
#97
b10100 ""
b10101 #"
b10110 $"
1%"
#98
0%"
#99
b10101 ""
b10110 #"
b10111 $"
1%"
#100
0%"
#101
b10110 ""
b10111 #"
b11000 $"
1%"
#102
0%"
#103
b10111 ""
b11000 #"
b11001 $"
1%"
#104
0%"
#105
b11000 ""
b11001 #"
b11010 $"
1%"
#106
0%"
#107
b11001 ""
b11010 #"
b11011 $"
1%"
#108
0%"
#109
b11010 ""
b11011 #"
b11100 $"
1%"
#110
0%"
#111
b11011 ""
b00000 #"
b11101 $"
1%"
#112
0%"
#113
b00000 ""
b00001 #"
b00010 $"
1%"
#114
0%"
#115
b00001 ""
b00010 #"
b00011 $"
1%"
#116
0%"
#117
b00010 ""
b00011 #"
b00100 $"
1%"
#118
0%"
#119
b00011 ""
b00100 #"
b00101 $"
1%"
#120
0%"
#121
b00100 ""
b00101 #"
b00110 $"
1%"
#122
0%"
#123
b00101 ""
b00110 #"
b00111 $"
1%"
#124
0%"
#125
b00110 ""
b00111 #"
b01000 $"
1%"
#126
0%"
#127
b00111 ""
b01000 #"
b01001 $"
1%"
#128
0%"
#129
b01000 ""
b01001 #"
b01010 $"
1%"
#130
0%"
#131
b01001 ""
b01010 #"
b01011 $"
1%"
#132
0%"
#133
b01010 ""
b01011 #"
b01100 $"
1%"
#134
0%"
#135
b01011 ""
b01100 #"
b01101 $"
1%"
#136
0%"
#137
b01100 ""
b01101 #"
b01110 $"
1%"
#138
0%"
#139
b01101 ""
b01110 #"
b01111 $"
1%"
#140
0%"
#141
b01110 ""
b01111 #"
b10000 $"
1%"
#142
0%"
#143
b01111 ""
b10000 #"
b10001 $"
1%"
#144
0%"
#145
b10000 ""
b10001 #"
b10010 $"
1%"
#146
0%"
#147
b10001 ""
b10010 #"
b10011 $"
1%"
#148
0%"
#149
b10010 ""
b10011 #"
b10100 $"
1%"
#150
0%"
#151
b10011 ""
b10100 #"
b10101 $"
1%"
#152
0%"
#153
b10100 ""
b10101 #"
b10110 $"
1%"
#154
0%"
#155
b10101 ""
b10110 #"
b10111 $"
1%"
#156
0%"
#157
b10110 ""
b10111 #"
b11000 $"
1%"
#158
0%"
#159
b10111 ""
b11000 #"
b11001 $"
1%"
#160
0%"
#161
b11000 ""
b11001 #"
b11010 $"
1%"
#162
0%"
#163
b11001 ""
b11010 #"
b11011 $"
1%"
#164
0%"
#165
b11010 ""
b11011 #"
b11100 $"
1%"
#166
0%"
#167
b11011 ""
b00000 #"
b11101 $"
1%"
#168
0%"
#169
b00000 ""
b00001 #"
b00010 $"
1%"
#170
0%"
#171
b00001 ""
b00010 #"
b00011 $"
1%"
#172
0%"
#173
b00010 ""
b00011 #"
b00100 $"
1%"
#174
0%"
#175
b00011 ""
b00100 #"
b00101 $"
1%"
#176
0%"
#177
b00100 ""
b00101 #"
b00110 $"
1%"
#178
0%"
#179
b00101 ""
b00110 #"
b00111 $"
1%"
#180
0%"
#181
b00110 ""
b00111 #"
b01000 $"
1%"
#182
0%"
#183
b00111 ""
b01000 #"
b01001 $"
1%"
#184
0%"
#185
b01000 ""
b01001 #"
b01010 $"
1%"
#186
0%"
#187
b01001 ""
b01010 #"
b01011 $"
1%"
#188
0%"
#189
b01010 ""
b01011 #"
b01100 $"
1%"
#190
0%"
#191
b01011 ""
b01100 #"
b01101 $"
1%"
#192
0%"
#193
b01100 ""
b01101 #"
b01110 $"
1%"
#194
0%"
#195
b01101 ""
b01110 #"
b01111 $"
1%"
#196
0%"
#197
b01110 ""
b01111 #"
b10000 $"
1%"
#198
0%"
#199
b01111 ""
b10000 #"
b10001 $"
1%"
#200
0%"
#201
b10000 ""
b10001 #"
b10010 $"
1%"
#202
0%"
#203
b10001 ""
b10010 #"
b10011 $"
1%"
#204
0%"
#205
b10010 ""
b10011 #"
b10100 $"
1%"
#206
0%"
#207
b10011 ""
b10100 #"
b10101 $"
1%"
#208
0%"
#209
b10100 ""
b10101 #"
b10110 $"
1%"
#210
0%"
#211
b10101 ""
b10110 #"
b10111 $"
1%"
#212
0%"
#213
b10110 ""
b10111 #"
b11000 $"
1%"
#214
0%"
#215
b10111 ""
b11000 #"
b11001 $"
1%"
#216
0%"
#217
b11000 ""
b11001 #"
b11010 $"
1%"
#218
0%"
#219
b11001 ""
b11010 #"
b11011 $"
1%"
#220
0%"
#221
b11010 ""
b11011 #"
b11100 $"
1%"
#222
0%"
#223
b11011 ""
b00000 #"
b11101 $"
1%"
#224
0%"
#225
b00000 ""
b00001 #"
b00010 $"
1%"
#226
0%"
#227
b00001 ""
b00010 #"
b00011 $"
1%"
#228
0%"
#229
b00010 ""
b00011 #"
b00100 $"
1%"
#230
0%"
#231
b00011 ""
b00100 #"
b00101 $"
1%"
#232
0%"
#233
b00100 ""
b00101 #"
b00110 $"
1%"
#234
0%"
#235
b00101 ""
b00110 #"
b00111 $"
1%"
#236
0%"
#237
b00110 ""
b00111 #"
b01000 $"
1%"
#238
0%"
#239
b00111 ""
b01000 #"
b01001 $"
1%"
#240
0%"
#241
b01000 ""
b01001 #"
b01010 $"
1%"
#242
0%"
#243
b01001 ""
b01010 #"
b01011 $"
1%"
#244
0%"
#245
b01010 ""
b01011 #"
b01100 $"
1%"
#246
0%"
#247
b01011 ""
b01100 #"
b01101 $"
1%"
#248
0%"
#249
b01100 ""
b01101 #"
b01110 $"
1%"
#250
0%"
#251
b00001011 #
b00001011 P
b00001011 v!
b00001011 {!
b01101 ""
b01110 #"
b01111 $"
1%"
b00001011 '"
#252
0%"
#253
b10010110 #
b00001011 $
b10010110 Q
b10010110 v!
b10010110 {!
b01110 ""
b01111 #"
b10000 $"
1%"
b10010110 '"
#254
0%"
#255
b11111101 #
b10010110 $
b00001011 %
b11111101 R
b11111101 v!
b11111101 {!
b01111 ""
b10000 #"
b10001 $"
1%"
b11111101 '"
#256
0%"
#257
b11001010 #
b11111101 $
b10010110 %
b00001011 &
b11001010 S
b11001010 v!
b11001010 {!
b10000 ""
b10001 #"
b10010 $"
1%"
b11001010 '"
#258
0%"
#259
b00011111 #
b11001010 $
b11111101 %
b10010110 &
b00001011 '
b00011111 T
b00011111 v!
b00011111 {!
b10001 ""
b10010 #"
b10011 $"
1%"
b00011111 '"
#260
0%"
#261
b00000000 #
b00011111 $
b11001010 %
b11111101 &
b10010110 '
b00000000 v!
b00000000 {!
b10010 ""
b10011 #"
b10100 $"
1%"
b00000000 '"
#262
0%"
#263
b00000000 $
b00011111 %
b11001010 &
b11111101 '
b10011 ""
b10100 #"
b10101 $"
1%"
#264
0%"
#265
b00000000 %
b00011111 &
b11001010 '
b10100 ""
b10101 #"
b10110 $"
1%"
#266
0%"
#267
b00000000 &
b00011111 '
b10101 ""
b10110 #"
b10111 $"
1%"
#268
0%"
#269
b00000000 '
b10110 ""
b10111 #"
b11000 $"
1%"
#270
0%"
#271
b10111 ""
b11000 #"
b11001 $"
1%"
#272
0%"
#273
b11000 ""
b11001 #"
b11010 $"
1%"
#274
0%"
#275
b11001 ""
b11010 #"
b11011 $"
1%"
#276
0%"
#277
b11010 ""
b11011 #"
b11100 $"
1%"
#278
0%"
#279
b11011 ""
b00000 #"
b11101 $"
1%"
#280
0%"
#281
b00000 ""
b00001 #"
b00010 $"
1%"
#282
0%"
#283
b00001 ""
b00010 #"
b00011 $"
1%"
#284
0%"
#285
b00010 ""
b00011 #"
b00100 $"
1%"
#286
0%"
#287
b00011 ""
b00100 #"
b00101 $"
1%"
#288
0%"
#289
b00100 ""
b00101 #"
b00110 $"
1%"
#290
0%"
#291
b00101 ""
b00110 #"
b00111 $"
1%"
#292
0%"
#293
b00110 ""
b00111 #"
b01000 $"
1%"
#294
0%"
#295
b00111 ""
b01000 #"
b01001 $"
1%"
#296
0%"
#297
b01000 ""
b01001 #"
b01010 $"
1%"
#298
0%"
#299
b01001 ""
b01010 #"
b01011 $"
1%"
#300
0%"
#301
b01010 ""
b01011 #"
b01100 $"
1%"
#302
0%"
#303
b01011 ""
b01100 #"
b01101 $"
1%"
#304
0%"
#305
b00001011 >
b00001011 C
b00001011 w!
b00001011 |!
b01100 ""
b01101 #"
b01110 $"
1%"
#306
0%"
#307
b00100101 #
b00001011 (
b10010110 >
b10010110 C
b00100101 P
b00001011 m
b00100101 v!
b10010110 w!
b00100101 {!
b10010110 |!
b01101 ""
b01110 #"
b01111 $"
1%"
b00100101 '"
#308
0%"
#309
b11111011 #
b00100101 $
b10010110 (
b00001011 )
b11111101 >
b11111101 C
b11111011 Q
b10010110 n
b11111011 v!
b11111101 w!
b11111011 {!
b11111101 |!
b01110 ""
b01111 #"
b10000 $"
1%"
b11111011 '"
#310
0%"
#311
b11111011 $
b00100101 %
b11111101 (
b10010110 )
b00001011 *
b11001010 >
b11001010 C
b11111011 R
b11111101 o
b11001010 w!
b11001010 |!
b01111 ""
b10000 #"
b10001 $"
1%"
#312
0%"
